setup.py
AioCacheBucket/__init__.py
AioCacheBucket/utils.py
AioCacheBucket.egg-info/PKG-INFO
AioCacheBucket.egg-info/SOURCES.txt
AioCacheBucket.egg-info/dependency_links.txt
AioCacheBucket.egg-info/requires.txt
AioCacheBucket.egg-info/top_level.txt